src/__init__.py
src/agents.py
src/api.py
src/cli.py
src/enums.py
src/exceptions.py
src/models.py
src/passage.py
src/reference.py
src/scripture_phaser.py
src/stats.py
src/verse.py
scripture_phaser-1.2.1.dist-info/METADATA
scripture_phaser-1.2.1.dist-info/WHEEL
scripture_phaser-1.2.1.dist-info/entry_points.txt
scripture_phaser-1.2.1.dist-info/licenses/LICENSE
scripture_phaser-1.2.1.dist-info/RECORD
