Metadata-Version: 2.3
Name: scripture_phaser
Version: 1.2.1
Summary: scripture_phaser helps you to memorize the Bible.
Project-URL: Homepage, https://nolanmcmahon.net/projects/scripture_phaser.html
Project-URL: Repository, https://github.com/NolantheNerd/scripture_phaser
Author-email: Nolan McMahon <nolan@nolanmcmahon.net>
License: Copyright 2023-2024 Nolan McMahon
License-File: LICENSE
Keywords: bible,bible-memorization,bible-study,christianity,cli,memorization,recitation,scripture
Classifier: Development Status :: 4 - Beta
Classifier: Environment :: Console
Classifier: Intended Audience :: End Users/Desktop
Classifier: Intended Audience :: Religion
Classifier: License :: OSI Approved :: BSD License
Classifier: Natural Language :: English
Classifier: Operating System :: MacOS
Classifier: Operating System :: Microsoft :: Windows
Classifier: Operating System :: Unix
Classifier: Programming Language :: Python
Classifier: Topic :: Religion
Requires-Python: >=3.8
Requires-Dist: meaningless==1.0.0
Requires-Dist: peewee==3.17.0
Requires-Dist: readchar==4.0.5
